f/__init__.py
f/chain_unit.py
f/lazy_string.py
f/proxy_module.py
fazy-0.0.10.dist-info/LICENSE
fazy-0.0.10.dist-info/METADATA
fazy-0.0.10.dist-info/WHEEL
fazy-0.0.10.dist-info/top_level.txt
fazy-0.0.10.dist-info/RECORD
